README.md
setup.py
object_modeler/__init__.py
object_modeler/common.py
object_modeler/dict_object_model.py
object_modeler/slots_object_model.py
object_modeler/yaml_model.py
object_modeler.egg-info/PKG-INFO
object_modeler.egg-info/SOURCES.txt
object_modeler.egg-info/dependency_links.txt
object_modeler.egg-info/requires.txt
object_modeler.egg-info/top_level.txt