Metadata-Version: 1.0
Name: object-modeler
Version: 1.0.3
Summary: Tool for clearly and simply definition of objects schemes
Home-page: https://github.com/KeyStorke/ObjectModeler
Author: Nickolay Ovdienko
Author-email: Nickolay.Ovdienko@emc.com
License: MIT
Platform: UNKNOWN
